README.md
setup.py
ustccomplex/__init__.py
ustccomplex/activations.py
ustccomplex/batchnorm.py
ustccomplex/conv.py
ustccomplex/distance.py
ustccomplex/functional.py
ustccomplex/linear.py
ustccomplex/loss.py
ustccomplex/rnn.py
ustccomplex.egg-info/PKG-INFO
ustccomplex.egg-info/SOURCES.txt
ustccomplex.egg-info/dependency_links.txt
ustccomplex.egg-info/requires.txt
ustccomplex.egg-info/top_level.txt