Metadata-Version: 1.0
Name: ustccomplex
Version: 0.2.0
Summary: A complex network toolbox
Home-page: UNKNOWN
Author: qstan
Author-email: tqs@mail.ustc.edu.cn
License: MIT Licence
Keywords: pip,ustccomplex,complex
Platform: any
